RobloxAccountMaker/__init__.py
RobloxAccountMaker-1.1.5.dist-info/LICENSE
RobloxAccountMaker-1.1.5.dist-info/METADATA
RobloxAccountMaker-1.1.5.dist-info/WHEEL
RobloxAccountMaker-1.1.5.dist-info/top_level.txt
RobloxAccountMaker-1.1.5.dist-info/RECORD
