Metadata-Version: 2.1
Name: RobloxAccountMaker
Version: 1.1.5
Summary: o7 Roblox Account Generator
Home-page: UNKNOWN
Author: o7-Fire
Author-email: <fireo7incorporated@gmail.com>
License: UNKNOWN
Keywords: python
Platform: UNKNOWN
Classifier: Development Status :: 3 - Alpha
Classifier: Intended Audience :: Education
Classifier: Programming Language :: Python :: 3
Classifier: Operating System :: Microsoft :: Windows
Requires-Dist: selenium
